<?xml version="1.0" encoding="UTF-8"?>
<tv>
  <channel id="9233005457">
    <display-name>NEW ENGLAND CABLE NEWS</display-name>
  </channel>
  <channel id="9200004312">
    <display-name>NESN</display-name>
  </channel>
  <channel id="9200006937">
    <display-name>ESPN</display-name>
  </channel>
  <channel id="9233008440">
    <display-name>FOX SPORTS 1</display-name>
  </channel>
  <channel id="9200009884">
    <display-name>FOX SPORTS 2</display-name>
  </channel>
  <channel id="9233005688">
    <display-name>NBA TV</display-name>
  </channel>
  <channel id="9233004106">
    <display-name>USA NETWORK</display-name>
  </channel>
  <channel id="9233011830">
    <display-name>TNT</display-name>
  </channel>
  <channel id="9233000403">
    <display-name>TBS</display-name>
  </channel>
  <channel id="9200009547">
    <display-name>TRU TV</display-name>
  </channel>
  <channel id="9200004889">
    <display-name>A&amp;E</display-name>
  </channel>
  <channel id="9233011832">
    <display-name>AMC</display-name>
  </channel>
  <channel id="9200006932">
    <display-name>FX</display-name>
  </channel>
  <channel id="9200004316">
    <display-name>SYFY</display-name>
  </channel>
  <channel id="9233006961">
    <display-name>IFC</display-name>
  </channel>
  <channel id="9233004104">
    <display-name>HGTV</display-name>
  </channel>
  <channel id="9233004112">
    <display-name>TLC</display-name>
  </channel>
  <channel id="9200019847">
    <display-name>DISCOVERY SCIENCE</display-name>
  </channel>
  <channel id="9200002243">
    <display-name>INVESTIGATION DISCOVERY</display-name>
  </channel>
  <channel id="9200018479">
    <display-name>ANIMAL PLANET</display-name>
  </channel>
  <channel id="9233002310">
    <display-name>NATIONAL GEOGRAPHIC</display-name>
  </channel>
  <channel id="9200002886">
    <display-name>BRAVO</display-name>
  </channel>
  <channel id="9200012343">
    <display-name>E! ENTERTAINMENT</display-name>
  </channel>
  <channel id="9200014754">
    <display-name>MTV</display-name>
  </channel>
  <channel id="9233000037">
    <display-name>VH1</display-name>
  </channel>
  <channel id="9233000169">
    <display-name>CMT</display-name>
  </channel>
  <channel id="9233005931">
    <display-name>BET</display-name>
  </channel>
  <channel id="9200002736">
    <display-name>OWN</display-name>
  </channel>
  <channel id="9200018188">
    <display-name>WE</display-name>
  </channel>
  <channel id="9200012145">
    <display-name>OXYGEN</display-name>
  </channel>
  <channel id="9200020464">
    <display-name>POP</display-name>
  </channel>
  <channel id="9200000630">
    <display-name>VICE</display-name>
  </channel>
  <channel id="9233015619">
    <display-name>REELZ</display-name>
  </channel>
  <channel id="9233000161">
    <display-name>FYI</display-name>
  </channel>
  <channel id="9233013354">
    <display-name>LOGO</display-name>
  </channel>
  <channel id="9233011488">
    <display-name>FUSE</display-name>
  </channel>
  <channel id="9200000846">
    <display-name>ASPIRE</display-name>
  </channel>
  <channel id="9200007166">
    <display-name>UP TV</display-name>
  </channel>
  <channel id="9200020469">
    <display-name>NICKELODEON</display-name>
  </channel>
  <channel id="9233003944">
    <display-name>GAME SHOW NETWORK</display-name>
  </channel>
  <channel id="9200009887">
    <display-name>INSP</display-name>
  </channel>
  <channel id="9200010020">
    <display-name>FETV</display-name>
  </channel>
  <channel id="9233003866">
    <display-name>TCM</display-name>
  </channel>
  <channel id="9233015768">
    <display-name>AMERICAN HEROES CHANNEL</display-name>
  </channel>
  <channel id="9200008780">
    <display-name>HBO</display-name>
  </channel>
  <channel id="9233000217">
    <display-name>FLIX</display-name>
  </channel>
  <channel id="9200012058">
    <display-name>STARZ</display-name>
  </channel>
  <channel id="9200009335">
    <display-name>MGM+</display-name>
  </channel>
</tv>
